pynvjitlink/CUDA_VERSION
pynvjitlink/GIT_COMMIT
pynvjitlink/VERSION
pynvjitlink/__init__.py
pynvjitlink/_nvjitlinklib.cpp
pynvjitlink/_nvjitlinklib.cpython-312-x86_64-linux-gnu.so
pynvjitlink/_version.py
pynvjitlink/api.py
pynvjitlink/patch.py
pynvjitlink/tests/conftest.py
pynvjitlink/tests/test_patch.py
pynvjitlink/tests/test_pynvjitlink.py
pynvjitlink/tests/test_pynvjitlink_api.py
pynvjitlink/tests/test_version.py
pynvjitlink_cu12-0.7.0.dist-info/METADATA
pynvjitlink_cu12-0.7.0.dist-info/WHEEL
pynvjitlink_cu12-0.7.0.dist-info/RECORD
pynvjitlink_cu12-0.7.0.dist-info/licenses/LICENSE
