Metadata-Version: 2.1
Name: pynvjitlink-cu12
Version: 0.7.0
Summary: nvJitLink Python binding
Author: NVIDIA Corporation
License: Apache-2.0
Project-URL: Homepage, https://rapids.ai/
Project-URL: Documentation, https://github.com/rapidsai/pynvjitlink/blob/main/README.md
Project-URL: Repository, https://github.com/rapidsai/pynvjitlink
Project-URL: License, https://github.com/rapidsai/pynvjitlink/blob/main/LICENSE
Requires-Python: >=3.10
Provides-Extra: test
Requires-Dist: cuda-python; extra == "test"
Requires-Dist: numba>=0.58; extra == "test"
Requires-Dist: psutil; extra == "test"
Requires-Dist: pytest; extra == "test"
Requires-Dist: pytest-cov; extra == "test"
